CHANGELOG.md
LICENSE
README.md
docs/conf.py
docs/index.rst
local_settings/__init__.py
local_settings/__main__.py
local_settings/base.py
local_settings/checker.py
local_settings/color_printer.py
local_settings/exc.py
local_settings/loader.py
local_settings/settings.py
local_settings/strategy.py
local_settings/types.py
local_settings/util.py
django_local_settings-2.0a9.dist-info/entry_points.txt
django_local_settings-2.0a9.dist-info/LICENSE
django_local_settings-2.0a9.dist-info/WHEEL
django_local_settings-2.0a9.dist-info/METADATA
django_local_settings-2.0a9.dist-info/RECORD
