Metadata-Version: 2.1
Name: django-local-settings
Version: 2.0a9
Summary: Define Django settings in config files and/or via environment variables
Home-page: https://github.com/wylee/django-local-settings
License: MIT
Keywords: django,settings,local,env,environment
Author: Wyatt Baldwin
Author-email: self@wyattbaldwin.com
Requires-Python: >=3.7,<4.0
Classifier: License :: OSI Approved :: MIT License
Classifier: Programming Language :: Python :: 3
Classifier: Programming Language :: Python :: 3.10
Classifier: Programming Language :: Python :: 3.7
Classifier: Programming Language :: Python :: 3.8
Classifier: Programming Language :: Python :: 3.9
Requires-Dist: Django (>=2.2)
Requires-Dist: jsun (>=1.0a1,<2.0)
Requires-Dist: python-dotenv (>=0.17.1,<0.18.0)
Project-URL: Repository, https://github.com/wylee/django-local-settings
